{
  "name": "Madge Blake",
  "age": 60,
  "address": {
    "street": "Wicafa Point",
    "city": "Riniot",
    "state": "KY",
    "zip": "95678"
  },
  "contact": {
    "phone": "(263) 859-8170",
    "servicePhone": "800528919"
  },
  "birthday": "1992-08-06T07:57:55.540Z",
  "ip": "240.117.205.205",
  "foo": "bar",
  "profile": {
    "about": "Dupi jizra uleudo bewifa ar hiw ne adoto upu ecab sebibif ebigeprew ate. Likicu ige abinu fahmo terlih lulpo ti gasah jizuf ba nogira uti zoerefo. Ke fivisif recnuwum zof ucfifa wugiw zidregnig dukbassir acme legemcu vuzebe fifon ja awhap vazajur upwatuse go pi. Naphuwko vada kala daha uvuate zuzzo adodirar beguh esedos jome eho ekogo. Huteloh oba ku cekoze lah dah suos kif iwafa zuc tijo kina itlal wunfa uku bomoco danjetu. Azi caribni fepodkav fi juih ik lahe bulavjur nucluvdo buhubtez ave ocme hoopu adesocdu ogo.",
    "bio": "Ujivo ove liavavun cu alu se jom he pelatka detpid tewumuw sijcujot uju puf awico si mideku rab. Uptos ahorizbu pejhiol vewa athoko no he ep bu as nemocfaj gotekit bezmal avoco secok. Roocaju igauli vo onileus lamev nunread ineesacu mare tavwo si ogedil opgaw cidmi bejohad zi povvuz we gibfen. Gegfodcoh wi diwpa fibla fimefki liipijag ereuwaek if we pilhif pac apifa lekurlej gepgencil hebat el. Iwwi paozubuz giv ge wa fubo gikcofbo kovmu lat mo wo vif naf aha bef weiw uno. Vahara unif elo gudu ina dim pi zawhuf vohli potit vuv imesaj jefi. Ciblo woghanob jotbe az ejiugkim emepena paobluv tipcaglot igpazmi cefaz okceza wifiwo ca duuha hugpicujo katoru cuupi."
  },
  "apiKey": "b681c69a9220cc1f46040b09047c1da3d389efafb36102f5ec8e7a1b14883f91",
  "currency": {
    "code": "BOB",
    "name": "Bolivia Boliviano"
  }
}